[1,["e0rkiPvahJ86D6c/O9Oc0L"],0,[["sp.SkeletonData",["_name","_atlasText","textureNames","_skeletonJson","textures"],-1,3]],[[0,0,1,2,3,4,5]],[[0,"nvwang1","\nnvwang1.png\nsize: 281,142\nformat: RGBA8888\nfilter: Linear,Linear\nrepeat: none\nerhuan\n  rotate: true\n  xy: 215, 52\n  size: 7, 6\n  orig: 7, 6\n  offset: 0, 0\n  index: -1\nerhuan2\n  rotate: true\n  xy: 215, 43\n  size: 7, 6\n  orig: 7, 6\n  offset: 0, 0\n  index: -1\nhaipa\n  rotate: false\n  xy: 2, 5\n  size: 26, 24\n  orig: 26, 24\n  offset: 0, 0\n  index: -1\nkaixin\n  rotate: true\n  xy: 87, 12\n  size: 26, 23\n  orig: 26, 23\n  offset: 0, 0\n  index: -1\nmaozi\n  rotate: false\n  xy: 112, 11\n  size: 48, 40\n  orig: 48, 40\n  offset: 0, 0\n  index: -1\nshengzihou\n  rotate: true\n  xy: 2, 31\n  size: 7, 83\n  orig: 7, 83\n  offset: 0, 0\n  index: -1\nshengziqian\n  rotate: true\n  xy: 162, 2\n  size: 17, 11\n  orig: 17, 11\n  offset: 0, 0\n  index: -1\nshou1\n  rotate: true\n  xy: 2, 40\n  size: 29, 108\n  orig: 29, 108\n  offset: 0, 0\n  index: -1\nshou2\n  rotate: true\n  xy: 2, 71\n  size: 30, 108\n  orig: 30, 108\n  offset: 0, 0\n  index: -1\nsiwang\n  rotate: false\n  xy: 30, 8\n  size: 22, 21\n  orig: 22, 21\n  offset: 0, 0\n  index: -1\ntou1\n  rotate: true\n  xy: 166, 21\n  size: 38, 47\n  orig: 38, 47\n  offset: 0, 0\n  index: -1\ntou2\n  rotate: true\n  xy: 223, 27\n  size: 38, 47\n  orig: 38, 47\n  offset: 0, 0\n  index: -1\ntoufa1\n  rotate: false\n  xy: 112, 53\n  size: 52, 48\n  orig: 52, 48\n  offset: 0, 0\n  index: -1\ntoufahou\n  rotate: false\n  xy: 166, 61\n  size: 55, 40\n  orig: 55, 40\n  offset: 0, 0\n  index: -1\ntui\n  rotate: false\n  xy: 2, 103\n  size: 277, 37\n  orig: 277, 37\n  offset: 0, 0\n  index: -1\nyifu\n  rotate: true\n  xy: 223, 67\n  size: 34, 55\n  orig: 34, 55\n  offset: 0, 0\n  index: -1\n",["nvwang1.png"],{"skeleton":{"hash":"ORmRyisYuDZVaHmVKBTYVxJqEbs","spine":"3.6.53","width":277.19,"height":244,"images":"./images/"},"bones":[{"name":"root"},{"name":"shengzihou","parent":"root","length":30,"rotation":-90,"x":-0.25,"y":-0.24},{"name":"tui","parent":"shengzihou","x":121.04,"y":0.25},{"name":"tui2","parent":"tui","length":44.47,"rotation":82.6,"x":0.46,"y":11.4},{"name":"tui3","parent":"tui2","length":49.91,"rotation":9.62,"x":44.47},{"name":"tui4","parent":"tui","length":42.98,"rotation":-85.74,"x":-0.46,"y":-10.49},{"name":"tui5","parent":"tui4","length":56.59,"rotation":-6.57,"x":42.98}],"slots":[{"name":"toufahou","bone":"tui","attachment":"toufahou"},{"name":"tui","bone":"tui","attachment":"tui"},{"name":"shengzihou","bone":"shengzihou","attachment":"shengzihou"},{"name":"shou1","bone":"tui","attachment":"shou1"},{"name":"shou2","bone":"tui","attachment":"shou2"},{"name":"shengziqian","bone":"tui","attachment":"shengziqian"},{"name":"yifu","bone":"tui","attachment":"yifu"},{"name":"erhuan2","bone":"tui","attachment":"erhuan2"},{"name":"tou1","bone":"tui","attachment":"tou2"},{"name":"kaixin","bone":"tui","attachment":"haipa"},{"name":"toufa1","bone":"tui","attachment":"toufa1"},{"name":"maozi","bone":"tui","attachment":"maozi"},{"name":"erhuan","bone":"tui","attachment":"erhuan"}],"skins":{"default":{"erhuan":{"erhuan":{"x":66.8,"y":-12.33,"rotation":90,"width":7,"height":6}},"erhuan2":{"erhuan2":{"x":69.8,"y":17.67,"rotation":90,"width":7,"height":6}},"kaixin":{"haipa":{"x":72.8,"y":4.17,"rotation":90,"width":26,"height":24},"kaixin":{"x":73.3,"y":4.17,"rotation":90,"width":26,"height":23},"siwang":{"x":73.3,"y":5.17,"rotation":90,"width":22,"height":21}},"maozi":{"maozi":{"x":105.8,"y":-7.83,"rotation":90,"width":48,"height":40}},"shengzihou":{"shengzihou":{"x":44.35,"y":-0.08,"rotation":90,"width":7,"height":83}},"shengziqian":{"shengziqian":{"x":-24.7,"y":-0.33,"rotation":90,"width":17,"height":11}},"shou1":{"shou1":{"x":6.8,"y":10.67,"rotation":90,"width":29,"height":108}},"shou2":{"shou2":{"x":6.8,"y":-9.83,"rotation":90,"width":30,"height":108}},"tou1":{"tou1":{"x":77.3,"y":-0.83,"rotation":90,"width":38,"height":47},"tou2":{"x":77.3,"y":-0.83,"rotation":90,"width":38,"height":47}},"toufa1":{"toufa1":{"x":78.8,"y":-5.83,"rotation":90,"width":52,"height":48}},"toufahou":{"toufahou":{"x":74.8,"y":1.67,"rotation":90,"width":55,"height":40}},"tui":{"tui":{"type":"mesh","hull":46,"width":277,"height":37,"uvs":[0.49371,0.18297,0.55133,0.0967,0.61059,0.24459,0.68138,0.26924,0.71759,0.28157,0.77686,0.24459,0.84435,0.26924,0.86658,0.13462,0.8888,0,0.94312,0,0.95734,0.11353,0.97156,0.22705,0.98578,0.34058,1,0.45411,1,0.56502,1,0.67594,1,0.78686,1,0.89778,0.95794,0.88546,0.87563,0.78686,0.81966,0.76221,0.71101,0.88546,0.62705,0.94708,0.5612,1,0.5217,1,0.42622,1,0.3011,0.91011,0.25336,0.87313,0.13978,0.74989,0.05911,0.87313,0,0.89778,0,0.80227,0,0.70675,0,0.61124,0,0.51573,0.01601,0.3868,0.03202,0.25786,0.04804,0.12893,0.06405,0,0.12825,0,0.14224,0.12846,0.15624,0.25692,0.27312,0.28157,0.31427,0.30621,0.39658,0.23227,0.44597,0.0967,0.46438,0.80386,0.8044,0.49776,0.5655,0.43097,0.27392,0.47813,0.63571,0.66462,0.28795,0.66692,0.14565,0.48914,0.44637,0.60861,0.66668,0.51792,0.82909,0.62294,0.65127,0.81238,0.39931,0.41123,0.86761,0.34604,0.31552,0.76877,0.49319,0.30041,0.1413,0.60115,0.90865,0.56286,0.54916,0.72213,0.47036,0.48933,0.71729,0.39092,0.1125,0.35056,0.33653,0.54263,0.21261,0.36068,0.55567,0.5723,0.41265,0.71416,0.40571,0.89661,0.75078,0.613,0.91311,0.44021],"triangles":[30,31,29,26,27,59,27,28,59,29,31,28,31,32,28,28,51,59,28,61,51,28,32,61,32,33,61,67,51,61,61,52,49,67,61,49,33,34,61,61,34,52,34,35,52,35,66,52,52,68,49,52,66,68,49,68,43,43,68,42,35,36,66,66,41,68,68,41,42,66,36,41,36,37,41,37,40,41,37,38,40,38,39,40,26,71,25,24,25,71,24,71,46,71,26,59,46,59,70,46,71,59,46,70,63,59,51,70,70,53,63,70,51,53,51,67,53,53,64,69,53,67,64,67,57,64,67,49,57,64,57,48,49,43,57,57,60,48,43,44,57,57,44,60,60,44,0,44,45,0,18,16,17,18,19,16,21,56,20,20,50,72,19,15,16,20,55,19,19,55,15,55,62,15,20,72,55,62,14,15,62,55,47,55,72,47,72,54,47,62,13,14,62,73,13,62,47,73,54,65,47,47,65,58,58,65,4,47,58,73,6,4,5,4,6,58,73,12,13,73,58,12,65,3,4,12,58,11,58,6,11,11,6,7,7,10,11,7,8,10,8,9,10,23,24,22,46,22,24,22,46,56,22,56,21,56,46,63,63,50,56,20,56,50,63,69,50,63,53,69,50,54,72,50,69,54,69,48,54,69,64,48,54,48,65,48,3,65,48,2,3,48,60,2,60,0,2,0,1,2],"vertices":[3,2,-13.43,-2.07,0.51437,3,-14.83,12.43,0.14317,5,-9.35,-12.31,0.34247,3,2,-16.62,13.89,0.18477,3,0.72,17.24,0.81418,5,-25.51,-14.31,0.00105,2,2,-11.15,30.3,0.00042,3,17.61,13.48,0.99958,2,3,37.21,14.58,0.81359,4,-4.3,15.71,0.18641,2,3,47.24,15.16,0.27041,4,5.64,14.34,0.72959,1,4,22.12,14.2,1,1,4,40.65,11.58,1,1,4,47.24,15.98,1,1,4,53.82,20.38,1,1,4,68.81,19.01,1,1,4,72.34,14.46,1,1,4,75.88,9.92,1,1,4,79.42,5.38,1,1,4,82.96,0.83,1,1,4,82.58,-3.25,1,1,4,82.21,-7.34,1,1,4,81.84,-11.43,1,1,4,81.46,-15.51,1,1,4,69.9,-13.99,1,1,4,47.53,-8.28,1,1,4,32.17,-5.95,1,2,3,47.71,-7.25,0.25221,4,1.79,-7.75,0.74779,1,3,24.81,-11.91,1,3,2,16.8,16.62,0.12024,3,6.87,-15.73,0.87969,5,-25.75,19.23,0.00007,3,2,16.8,5.68,0.45414,3,-4.02,-16.85,0.47051,5,-14.84,18.41,0.07535,2,2,16.8,-20.77,0.0546,5,11.54,16.45,0.9454,2,5,45.85,10.56,0.3282,6,1.64,10.82,0.6718,1,6,14.91,9.98,1,1,6,46.53,6.69,1,1,6,68.67,12.15,1,1,6,85,13.72,1,1,6,85.14,10.19,1,1,6,85.28,6.66,1,1,6,85.42,3.13,1,1,6,85.57,-0.4,1,1,6,81.33,-5.35,1,1,6,77.09,-10.29,1,1,6,72.85,-15.24,1,1,6,68.61,-20.18,1,1,6,50.84,-20.9,1,1,6,46.77,-16.31,1,1,6,42.71,-11.72,1,2,5,51.85,-13.21,0.02853,6,10.32,-12.11,0.97147,2,5,40.55,-11.45,0.60885,6,-1.11,-11.66,0.39115,1,5,17.61,-12.49,1,2,2,-16.62,-15.3,0.08318,5,3.6,-16.47,0.91682,3,2,9.55,-10.2,0.26184,3,-20.55,-11.26,0.00627,5,0.45,10,0.73189,1,4,28.86,4.18,1,2,2,-4.25,17.81,0.01258,3,5.89,5.34,0.98742,2,5,52.17,-5.94,0.0089,6,9.81,-4.85,0.9911,1,3,26.13,-1.27,1,1,6,5.64,1.97,1,1,6,45.29,-3.01,1,2,2,2.32,-15.19,0.01191,5,4.89,2.42,0.98809,2,3,34.11,5.01,0.98585,4,-9.2,6.92,0.01415,1,4,35.25,-1.06,1,1,3,30.97,-6.26,1,1,5,17.35,-5.83,1,1,4,46.81,8.17,1,2,5,41.48,5.64,0.61573,6,-2.14,5.43,0.38427,3,2,-9.08,-2.22,0.56521,3,-14.52,8.09,0.10982,5,-8.89,-7.99,0.32497,1,6,46.33,1.18,1,1,4,57.39,-0.86,1,2,2,6.52,13.29,0.10491,3,2.5,-5.84,0.89509,2,2,-2.09,-8.54,0.16914,5,-2.06,-1.49,0.83086,2,3,47.57,11.12,0.255,4,5.19,10.32,0.745,1,6,54.67,-7.77,1,2,5,35.05,-2.27,0.99368,6,-7.62,-3.16,0.00632,1,6,26.95,-8.51,1,1,3,3.72,-0.14,1,2,2,6.23,-24.53,0.00417,5,14.5,5.62,0.99583,2,2,12.98,-26.45,0.00952,5,16.91,12.21,0.99048,2,3,57.64,3.9,0.00104,4,13.68,1.29,0.99896,1,4,59.04,3.55,1],"edges":[0,2,2,4,4,6,6,8,8,10,10,12,12,14,14,16,16,18,18,20,20,22,22,24,24,26,26,28,28,30,30,32,32,34,34,36,36,38,38,40,40,42,42,44,44,46,46,48,48,50,50,52,52,54,54,56,56,58,58,60,60,62,62,64,64,66,66,68,68,70,70,72,72,74,74,76,76,78,78,80,80,82,82,84,84,86,86,88,88,90,90,0]}},"yifu":{"yifu":{"x":41.3,"y":0.17,"rotation":90,"width":34,"height":55}}}},"animations":{"idle1":{"slots":{"kaixin":{"attachment":[{"time":0,"name":"haipa"}]},"tou1":{"attachment":[{"time":0,"name":"tou1"}]}},"bones":{"tui2":{"rotate":[{"time":0,"angle":24.18,"curve":[0.25,0,0.75,1]},{"time":0.5,"angle":5.8,"curve":[0.25,0,0.75,1]},{"time":1,"angle":24.18}],"translate":[{"time":0,"x":0,"y":0,"curve":"stepped"},{"time":1,"x":0,"y":0}],"scale":[{"time":0,"x":1,"y":1,"curve":"stepped"},{"time":1,"x":1,"y":1}]},"tui4":{"rotate":[{"time":0,"angle":-2.37,"curve":[0.25,0,0.75,1]},{"time":0.5,"angle":-20.75,"curve":[0.25,0,0.75,1]},{"time":1,"angle":-2.37}],"translate":[{"time":0,"x":0,"y":0,"curve":"stepped"},{"time":1,"x":0,"y":0}],"scale":[{"time":0,"x":1,"y":1,"curve":"stepped"},{"time":1,"x":1,"y":1}]},"tui":{"translate":[{"time":0,"x":0,"y":0,"curve":"stepped"},{"time":0.5,"x":0,"y":0,"curve":"stepped"},{"time":1,"x":0,"y":0}],"scale":[{"time":0,"x":1,"y":1},{"time":0.2333,"x":1.035,"y":0.972},{"time":0.5,"x":1,"y":1},{"time":0.7333,"x":1.035,"y":0.972},{"time":1,"x":1,"y":1}]},"shengzihou":{"rotate":[{"time":0,"angle":-5.53,"curve":[0.25,0,0.75,1]},{"time":0.5,"angle":6.02,"curve":[0.25,0,0.75,1]},{"time":1,"angle":-5.53}],"translate":[{"time":0,"x":0,"y":0,"curve":"stepped"},{"time":1,"x":0,"y":0}],"scale":[{"time":0,"x":1,"y":1,"curve":"stepped"},{"time":1,"x":1,"y":1}]},"tui3":{"rotate":[{"time":0,"angle":3.39,"curve":[0.381,0.55,0.742,1]},{"time":0.2,"angle":10.16,"curve":[0.25,0,0.75,1]},{"time":0.7,"angle":-8.22,"curve":[0.245,0,0.637,0.56]},{"time":1,"angle":3.39}]},"tui5":{"rotate":[{"time":0,"angle":3.39,"curve":[0.381,0.55,0.742,1]},{"time":0.2,"angle":10.16,"curve":[0.25,0,0.75,1]},{"time":0.7,"angle":-8.22,"curve":[0.245,0,0.637,0.56]},{"time":1,"angle":3.39}]}}},"idle2":{"bones":{"tui2":{"rotate":[{"time":0,"angle":14.02},{"time":0.1,"angle":4.19},{"time":0.1667,"angle":14.02},{"time":0.2667,"angle":4.19},{"time":0.3333,"angle":14.02},{"time":0.4333,"angle":4.19},{"time":0.5,"angle":14.02},{"time":0.6,"angle":4.19},{"time":0.6667,"angle":14.02},{"time":0.7667,"angle":4.19},{"time":0.8333,"angle":14.02},{"time":0.9333,"angle":4.19},{"time":1,"angle":14.02}],"translate":[{"time":0,"x":0,"y":0,"curve":"stepped"},{"time":0.1,"x":0,"y":0,"curve":"stepped"},{"time":0.1667,"x":0,"y":0,"curve":"stepped"},{"time":0.2667,"x":0,"y":0,"curve":"stepped"},{"time":0.3333,"x":0,"y":0,"curve":"stepped"},{"time":0.4333,"x":0,"y":0,"curve":"stepped"},{"time":0.5,"x":0,"y":0,"curve":"stepped"},{"time":0.6,"x":0,"y":0,"curve":"stepped"},{"time":0.6667,"x":0,"y":0,"curve":"stepped"},{"time":0.7667,"x":0,"y":0,"curve":"stepped"},{"time":0.8333,"x":0,"y":0,"curve":"stepped"},{"time":0.9333,"x":0,"y":0,"curve":"stepped"},{"time":1,"x":0,"y":0}],"scale":[{"time":0,"x":1,"y":1,"curve":"stepped"},{"time":0.1,"x":1,"y":1,"curve":"stepped"},{"time":0.1667,"x":1,"y":1,"curve":"stepped"},{"time":0.2667,"x":1,"y":1,"curve":"stepped"},{"time":0.3333,"x":1,"y":1,"curve":"stepped"},{"time":0.4333,"x":1,"y":1,"curve":"stepped"},{"time":0.5,"x":1,"y":1,"curve":"stepped"},{"time":0.6,"x":1,"y":1,"curve":"stepped"},{"time":0.6667,"x":1,"y":1,"curve":"stepped"},{"time":0.7667,"x":1,"y":1,"curve":"stepped"},{"time":0.8333,"x":1,"y":1,"curve":"stepped"},{"time":0.9333,"x":1,"y":1,"curve":"stepped"},{"time":1,"x":1,"y":1}]},"tui4":{"rotate":[{"time":0,"angle":-12.52},{"time":0.1,"angle":-1.74},{"time":0.1667,"angle":-12.52},{"time":0.2667,"angle":-1.74},{"time":0.3333,"angle":-12.52},{"time":0.4333,"angle":-1.74},{"time":0.5,"angle":-12.52},{"time":0.6,"angle":-1.74},{"time":0.6667,"angle":-12.52},{"time":0.7667,"angle":-1.74},{"time":0.8333,"angle":-12.52},{"time":0.9333,"angle":-1.74},{"time":1,"angle":-12.52}],"translate":[{"time":0,"x":0,"y":0,"curve":"stepped"},{"time":0.1,"x":0,"y":0,"curve":"stepped"},{"time":0.1667,"x":0,"y":0,"curve":"stepped"},{"time":0.2667,"x":0,"y":0,"curve":"stepped"},{"time":0.3333,"x":0,"y":0,"curve":"stepped"},{"time":0.4333,"x":0,"y":0,"curve":"stepped"},{"time":0.5,"x":0,"y":0,"curve":"stepped"},{"time":0.6,"x":0,"y":0,"curve":"stepped"},{"time":0.6667,"x":0,"y":0,"curve":"stepped"},{"time":0.7667,"x":0,"y":0,"curve":"stepped"},{"time":0.8333,"x":0,"y":0,"curve":"stepped"},{"time":0.9333,"x":0,"y":0,"curve":"stepped"},{"time":1,"x":0,"y":0}],"scale":[{"time":0,"x":1,"y":1,"curve":"stepped"},{"time":0.1,"x":1,"y":1,"curve":"stepped"},{"time":0.1667,"x":1,"y":1,"curve":"stepped"},{"time":0.2667,"x":1,"y":1,"curve":"stepped"},{"time":0.3333,"x":1,"y":1,"curve":"stepped"},{"time":0.4333,"x":1,"y":1,"curve":"stepped"},{"time":0.5,"x":1,"y":1,"curve":"stepped"},{"time":0.6,"x":1,"y":1,"curve":"stepped"},{"time":0.6667,"x":1,"y":1,"curve":"stepped"},{"time":0.7667,"x":1,"y":1,"curve":"stepped"},{"time":0.8333,"x":1,"y":1,"curve":"stepped"},{"time":0.9333,"x":1,"y":1,"curve":"stepped"},{"time":1,"x":1,"y":1}]},"tui":{"translate":[{"time":0,"x":0,"y":0,"curve":"stepped"},{"time":0.5,"x":0,"y":0,"curve":"stepped"},{"time":1,"x":0,"y":0}],"scale":[{"time":0,"x":1,"y":1},{"time":0.2333,"x":1.035,"y":0.972},{"time":0.5,"x":1,"y":1},{"time":0.7333,"x":1.035,"y":0.972},{"time":1,"x":1,"y":1}]},"shengzihou":{"rotate":[{"time":0,"angle":-5.53,"curve":[0.25,0,0.75,1]},{"time":0.5,"angle":6.02,"curve":[0.25,0,0.75,1]},{"time":1,"angle":-5.53}],"translate":[{"time":0,"x":0,"y":0,"curve":"stepped"},{"time":1,"x":0,"y":0}],"scale":[{"time":0,"x":1,"y":1,"curve":"stepped"},{"time":1,"x":1,"y":1}]}}},"win":{"slots":{"kaixin":{"attachment":[{"time":0,"name":"kaixin"}]},"tou1":{"attachment":[{"time":0,"name":"tou1"}]}},"bones":{"tui2":{"rotate":[{"time":0,"angle":24.18,"curve":[0.25,0,0.75,1]},{"time":0.5,"angle":5.8,"curve":[0.25,0,0.75,1]},{"time":1,"angle":24.18}],"translate":[{"time":0,"x":0,"y":0,"curve":"stepped"},{"time":1,"x":0,"y":0}],"scale":[{"time":0,"x":1,"y":1,"curve":"stepped"},{"time":1,"x":1,"y":1}]},"tui4":{"rotate":[{"time":0,"angle":-2.37,"curve":[0.25,0,0.75,1]},{"time":0.5,"angle":-20.75,"curve":[0.25,0,0.75,1]},{"time":1,"angle":-2.37}],"translate":[{"time":0,"x":0,"y":0,"curve":"stepped"},{"time":1,"x":0,"y":0}],"scale":[{"time":0,"x":1,"y":1,"curve":"stepped"},{"time":1,"x":1,"y":1}]},"tui":{"translate":[{"time":0,"x":0,"y":0,"curve":"stepped"},{"time":0.5,"x":0,"y":0,"curve":"stepped"},{"time":1,"x":0,"y":0}],"scale":[{"time":0,"x":1,"y":1},{"time":0.2333,"x":1.035,"y":0.972},{"time":0.5,"x":1,"y":1},{"time":0.7333,"x":1.035,"y":0.972},{"time":1,"x":1,"y":1}]},"shengzihou":{"rotate":[{"time":0,"angle":-5.53,"curve":[0.25,0,0.75,1]},{"time":0.5,"angle":6.02,"curve":[0.25,0,0.75,1]},{"time":1,"angle":-5.53}],"translate":[{"time":0,"x":0,"y":0,"curve":"stepped"},{"time":1,"x":0,"y":0}],"scale":[{"time":0,"x":1,"y":1,"curve":"stepped"},{"time":1,"x":1,"y":1}]},"tui3":{"rotate":[{"time":0,"angle":3.39,"curve":[0.381,0.55,0.742,1]},{"time":0.2,"angle":10.16,"curve":[0.25,0,0.75,1]},{"time":0.7,"angle":-8.22,"curve":[0.245,0,0.637,0.56]},{"time":1,"angle":3.39}]},"tui5":{"rotate":[{"time":0,"angle":3.39,"curve":[0.381,0.55,0.742,1]},{"time":0.2,"angle":10.16,"curve":[0.25,0,0.75,1]},{"time":0.7,"angle":-8.22,"curve":[0.245,0,0.637,0.56]},{"time":1,"angle":3.39}]}}}}},[0]]],0,0,[0],[-1],[0]]